nonebot_plugin_whats_talk_qwen/__init__.py
nonebot_plugin_whats_talk_qwen/config.py
nonebot_plugin_whats_talk_qwen-0.0.2.dist-info/METADATA
nonebot_plugin_whats_talk_qwen-0.0.2.dist-info/WHEEL
nonebot_plugin_whats_talk_qwen-0.0.2.dist-info/licenses/LICENSE
nonebot_plugin_whats_talk_qwen-0.0.2.dist-info/RECORD
