Metadata-Version: 2.4
Name: nonebot-plugin-whats-talk-qwen
Version: 0.0.2
Summary: 分析群聊记录，生成近期讨论话题的总结。
License-File: LICENSE
Keywords: nonebot,nonebot2,plugin
Author: qianqiuzy
Author-email: qianqiuzy@gmail.com
Requires-Python: >=3.9,<4.0
Classifier: Programming Language :: Python :: 3
Classifier: Programming Language :: Python :: 3.9
Classifier: Programming Language :: Python :: 3.10
Classifier: Programming Language :: Python :: 3.11
Classifier: Programming Language :: Python :: 3.12
Classifier: Programming Language :: Python :: 3.13
Classifier: Programming Language :: Python :: 3.14
Requires-Dist: httpx (>=0.27,<0.28)
Requires-Dist: nonebot-adapter-onebot (>=2.0.0-beta.1)
Requires-Dist: nonebot2 (>=2.3.0,<3.0.0)
Requires-Dist: nonebot_plugin_apscheduler (>=0.5.0,<0.6.0)
Project-URL: Repository, https://github.com/qianqiuzy/nonebot-plugin-whats-talk-qwen
